Workbook

Sheet 🏥 Health Scoring
A1: CUSTOMER HEALTH SCORING DASHBOARD · Director of Customer Success · Cernice Robinson
A2: Composite health model · Dual-lane risk detection · Updated monthly per QBR cycle
A4: HEALTH SCORE LEGEND | F4: RISK TIER DEFINITIONS | J4: SIGNAL WEIGHTS (Composite Model)
A5: Score Range | B5: Rating | C5: Action | D5: Owner | F5: Tier | G5: Definition | H5: Frequency | I5: Flag Trigger | J5: Signal | K5: Weight | L5: Data Source | M5: Cadence | N5: Notes
A6: 85 – 100 | B6: 🟢 Healthy | C6: Expand / Upsell | D6: CSM | F6: Enterprise | G6: $500K+ ARR | H6: Monthly QBR | I6: Any 2 signals drop | J6: Product Adoption / Usage | K6: 30% | L6: Product Analytics | M6: Weekly | N6: DAU/MAU ratio
A7: 70 – 84 | B7: 🟡 Monitor | C7: Proactive Check-In | D7: CSM | F7: Mid-Market | G7: $100K–499K ARR | H7: Bi-monthly | I7: Score < 70 | J7: Support Health (CSAT/tickets) | K7: 25% | L7: Helpdesk / CSAT | M7: Real-time | N7: Ticket vol + sentiment
A8: 50 – 69 | B8: 🟠 At Risk | C8: Intervention Plan | D8: CS Director | F8: Growth | G8: $25K–99K ARR | H8: Quarterly | I8: Score < 60 | J8: Engagement (touchpoints) | K8: 20% | L8: CRM / CS Platform | M8: Monthly | N8: Response time trends
A9: < 50 | B9: 🔴 Critical | C9: Executive Escalation | D9: VP / C-Suite | F9: SMB | G9: < $25K ARR | H9: Self-serve + alerts | I9: Score < 50 | J9: Financial Health (ARR, invoices) | K9: 15% | L9: Billing System | M9: Monthly | N9: Payment timing
J10: Executive Relationship | K10: 10% | L10: CSM Notes / QBR | M10: Quarterly | N10: Sponsor access
A12: ACCOUNT HEALTH SCORECARD · Q1 2025 · 200+ Enterprise Portfolio Sample
A13: Account Name | B13: Tier | C13: CSM Owner | D13: ARR ($K) | E13: Adoption % | F13: CSAT | G13: Engagement | H13: Financial | I13: Exec Rel | J13: COMPOSITE SCORE | K13: Risk Rating | L13: Trend | M13: Last QBR | N13: Next Action
A14: Walmart | B14: Enterprise | C14: Cernice R. | D14: 2400 | E14: 0.92 | F14: 4.8 | G14: 0.88 | H14: 1 | I14: 0.95 | J14: =E14*0.3 + (F14/5)*0.25 + G14*0.2 + H14*0.15 + I14*0.1 -> 0.937 | K14: =IF(J14>=0.85,"🟢 Healthy",IF(J14>=0.7,"🟡 Monitor",IF(J14>=0.5,"🟠 At Risk","🔴 Critical"))) -> 🟢 Healthy | L14: ↑ Improving | M14: Jan 15 2025 | N14: Expansion proposal
A15: Kroger | B15: Enterprise | C15: Cernice R. | D15: 1800 | E15: 0.87 | F15: 4.6 | G15: 0.82 | H15: 0.98 | I15: 0.9 | J15: =E15*0.3 + (F15/5)*0.25 + G15*0.2 + H15*0.15 + I15*0.1 -> 0.892 | K15: =IF(J15>=0.85,"🟢 Healthy",IF(J15>=0.7,"🟡 Monitor",IF(J15>=0.5,"🟠 At Risk","🔴 Critical"))) -> 🟢 Healthy | L15: → Stable | M15: Jan 22 2025 | N15: QBR scheduled Feb
A16: Jewel-Osco | B16: Enterprise | C16: Cernice R. | D16: 950 | E16: 0.79 | F16: 4.4 | G16: 0.75 | H16: 0.95 | I16: 0.85 | J16: =E16*0.3 + (F16/5)*0.25 + G16*0.2 + H16*0.15 + I16*0.1 -> 0.8345 | K16: =IF(J16>=0.85,"🟢 Healthy",IF(J16>=0.7,"🟡 Monitor",IF(J16>=0.5,"🟠 At Risk","🔴 Critical"))) -> 🟡 Monitor | L16: → Stable | M16: Feb 01 2025 | N16: Feature adoption push
A17: Meijer | B17: Enterprise | C17: T. Williams | D17: 1200 | E17: 0.71 | F17: 4.1 | G17: 0.68 | H17: 0.92 | I17: 0.8 | J17: =E17*0.3 + (F17/5)*0.25 + G17*0.2 + H17*0.15 + I17*0.1 -> 0.772 | K17: =IF(J17>=0.85,"🟢 Healthy",IF(J17>=0.7,"🟡 Monitor",IF(J17>=0.5,"🟠 At Risk","🔴 Critical"))) -> 🟡 Monitor | L17: ↓ Declining | M17: Jan 08 2025 | N17: ⚠ Intervention plan
A18: Safeway | B18: Enterprise | C18: T. Williams | D18: 880 | E18: 0.65 | F18: 3.9 | G18: 0.6 | H18: 0.88 | I18: 0.72 | J18: =E18*0.3 + (F18/5)*0.25 + G18*0.2 + H18*0.15 + I18*0.1 -> 0.714 | K18: =IF(J18>=0.85,"🟢 Healthy",IF(J18>=0.7,"🟡 Monitor",IF(J18>=0.5,"🟠 At Risk","🔴 Critical"))) -> 🟡 Monitor | L18: ↓ Declining | M18: Dec 12 2024 | N18: 🔴 Executive call req.
A19: Albertsons | B19: Mid-Market | C19: J. Patel | D19: 420 | E19: 0.88 | F19: 4.7 | G19: 0.85 | H19: 0.97 | I19: 0.88 | J19: =E19*0.3 + (F19/5)*0.25 + G19*0.2 + H19*0.15 + I19*0.1 -> 0.9025 | K19: =IF(J19>=0.85,"🟢 Healthy",IF(J19>=0.7,"🟡 Monitor",IF(J19>=0.5,"🟠 At Risk","🔴 Critical"))) -> 🟢 Healthy | L19: ↑ Improving | M19: Feb 05 2025 | N19: Upsell conversation
A20: Fresh Market | B20: Mid-Market | C20: J. Patel | D20: 310 | E20: 0.74 | F20: 4.2 | G20: 0.7 | H20: 0.9 | I20: 0.78 | J20: =E20*0.3 + (F20/5)*0.25 + G20*0.2 + H20*0.15 + I20*0.1 -> 0.785 | K20: =IF(J20>=0.85,"🟢 Healthy",IF(J20>=0.7,"🟡 Monitor",IF(J20>=0.5,"🟠 At Risk","🔴 Critical"))) -> 🟡 Monitor | L20: → Stable | M20: Jan 28 2025 | N20: Renewal prep
A21: Sprouts | B21: Mid-Market | C21: J. Patel | D21: 285 | E21: 0.55 | F21: 3.6 | G21: 0.5 | H21: 0.82 | I21: 0.6 | J21: =E21*0.3 + (F21/5)*0.25 + G21*0.2 + H21*0.15 + I21*0.1 -> 0.628 | K21: =IF(J21>=0.85,"🟢 Healthy",IF(J21>=0.7,"🟡 Monitor",IF(J21>=0.5,"🟠 At Risk","🔴 Critical"))) -> 🟠 At Risk | L21: ↓ Declining | M21: Dec 20 2024 | N21: ⚠ At-risk recovery
A22: Aldi | B22: Growth | C22: M. Chen | D22: 140 | E22: 0.82 | F22: 4.5 | G22: 0.8 | H22: 0.94 | I22: 0.82 | J22: =E22*0.3 + (F22/5)*0.25 + G22*0.2 + H22*0.15 + I22*0.1 -> 0.854 | K22: =IF(J22>=0.85,"🟢 Healthy",IF(J22>=0.7,"🟡 Monitor",IF(J22>=0.5,"🟠 At Risk","🔴 Critical"))) -> 🟢 Healthy | L22: → Stable | M22: Feb 10 2025 | N22: Nurture / expand
A23: Trader Joes | B23: Growth | C23: M. Chen | D23: 120 | E23: 0.45 | F23: 3.2 | G23: 0.42 | H23: 0.75 | I23: 0.5 | J23: =E23*0.3 + (F23/5)*0.25 + G23*0.2 + H23*0.15 + I23*0.1 -> 0.5415 | K23: =IF(J23>=0.85,"🟢 Healthy",IF(J23>=0.7,"🟡 Monitor",IF(J23>=0.5,"🟠 At Risk","🔴 Critical"))) -> 🟠 At Risk | L23: ↓ Declining | M23: Nov 30 2024 | N23: 🔴 Churn risk — act now
A24: PORTFOLIO SUMMARY | D24: =SUM(D14:D23) -> 8505 | E24: =AVERAGE(E14:E23) -> 0.738 | J24: =AVERAGE(J14:J23) -> 0.78605

Sheet 📋 QBR & Account Planning
A1: QBR PREPARATION & ACCOUNT PLANNING TEMPLATE · Cernice Robinson, Director of Customer Success
A2: Structured QBR framework · Executive engagement · Value demonstration · Forward roadmap
A4: SECTION 1 — ACCOUNT OVERVIEW & RELATIONSHIP STATUS
A5: Account | B5: ARR ($K) | C5: Contract End | D5: Health Score | E5: Executive Sponsor | F5: CSM | G5: QBR Date | H5: Format | I5: Attendees (Client) | J5: Attendees (Internal) | K5: Prep Status | L5: Priority
A6: Walmart | B6: 2400 | C6: Dec 2025 | D6: =VLOOKUP(A6,'🏥 Health Scoring'!A14:N23,10,FALSE()) -> 0.937 | E6: Sarah Chen (EVP) | F6: Cernice R. | G6: Feb 15 2025 | H6: In-Person | I6: EVP + VP Ops + Dir IT | J6: Cernice + VP CS + AE | K6: ✅ Ready | L6: P1 - Critical
A7: Kroger | B7: 1800 | C7: Mar 2025 | D7: =VLOOKUP(A7,'🏥 Health Scoring'!A14:N23,10,FALSE()) -> 0.892 | E7: Mike Torres (SVP) | F7: Cernice R. | G7: Feb 22 2025 | H7: Hybrid | I7: SVP + Dir Procurement | J7: Cernice + AE | K7: 🔄 In Progress | L7: P1 - Critical
A8: Meijer | B8: 1200 | C8: Jun 2025 | D8: =VLOOKUP(A8,'🏥 Health Scoring'!A14:N23,10,FALSE()) -> 0.772 | E8: Jim Rao (VP) | F8: T. Williams | G8: Mar 05 2025 | H8: Virtual | I8: VP + 2 Managers | J8: Cernice + CSM | K8: ⚠ At Risk | L8: P1 - Critical
A9: Safeway | B9: 880 | C9: Sep 2025 | D9: =VLOOKUP(A9,'🏥 Health Scoring'!A14:N23,10,FALSE()) -> 0.714 | E9: Dana Webb (Dir) | F9: T. Williams | G9: Mar 12 2025 | H9: Virtual | I9: Dir + Ops Lead | J9: Cernice + CSM + AE | K9: 🔴 Not Started | L9: P2 - High
A10: Albertsons | B10: 420 | C10: Nov 2025 | D10: =VLOOKUP(A10,'🏥 Health Scoring'!A14:N23,10,FALSE()) -> 0.9025 | E10: Lisa Park (Mgr) | F10: J. Patel | G10: Mar 20 2025 | H10: Virtual | I10: Mgr + Analyst | J10: CSM | K10: ✅ Ready | L10: P2 - High
A13: SECTION 2 — STANDARD QBR AGENDA TEMPLATE · 90-Minute Executive Format
A14: # | B14: Agenda Item | C14: Owner | D14: Duration | E14: Talking Points | F14: Success Metric | G14: Slide Ref | H14: Pre-Read? | I14: Client Action? | J14: Internal Note | K14: Status | L14: Time Block
A15: 1 | B15: Executive Welcome & Agenda Review | C15: Client Exec | D15: 5 min | E15: Set tone, confirm agenda, intro attendees | F15: Engaged executives in room | G15: Slide 1 | H15: No | I15: No | J15: Let client open — positions them as host | K15: ✅ | L15: 0:00–0:05
A16: 2 | B16: Partnership Health Snapshot | C16: CSM / Director | D16: 10 min | E16: Score, trend, NPS, key wins vs. last QBR | F16: Client validates scores | G16: Slides 2-4 | H16: Yes | I16: No | J16: Lead with wins before gaps | K16: ✅ | L16: 0:05–0:15
A17: 3 | B17: ROI & Value Delivered | C17: CSM | D17: 15 min | E17: Quantified outcomes, cost savings, efficiency gains | F17: Client confirms 2+ specific outcomes | G17: Slides 5-8 | H17: Yes | I17: No | J17: Use client's own data — more credible | K17: ✅ | L17: 0:15–0:30
A18: 4 | B18: Product Adoption Deep Dive | C18: CSM | D18: 15 min | E18: Feature usage heatmap, underutilized capabilities | F18: Identify 1 adoption growth area | G18: Slides 9-11 | H18: No | I18: Yes | J18: Frame gaps as opportunities, not failures | K18: 🔄 | L18: 0:30–0:45
A19: 5 | B19: Challenges & Open Issues | C19: Both | D19: 10 min | E19: Address open tickets, escalations, concerns | F19: All open items have owner + date | G19: Slide 12 | H19: Yes | I19: Yes | J19: Never surprise client — pre-discuss issues | K19: ✅ | L19: 0:45–0:55
A20: 6 | B20: Strategic Roadmap Preview | C20: Director | D20: 15 min | E20: Upcoming features, integrations, roadmap alignment | F20: Client sees clear future value | G20: Slides 13-15 | H20: No | I20: No | J20: Tie roadmap to their stated business goals | K20: 🔄 | L20: 0:55–1:10
A21: 7 | B21: Joint Success Plan — Next 90 Days | C21: Both | D21: 10 min | E21: 3–5 mutual commitments, owners, due dates | F21: Written plan agreed by both parties | G21: Slide 16 | H21: No | I21: Yes | J21: Document in Gainsight immediately after | K21: ✅ | L21: 1:10–1:20
A22: 8 | B22: Executive Ask / Expansion Discussion | C22: Director | D22: 5 min | E22: NPS survey, case study, referral, or upsell signal | F22: Clear next step identified | G22: Slide 17 | H22: No | I22: Yes | J22: Only if health > 75 — do NOT in red accounts | K22: 🔄 | L22: 1:20–1:25
A23: 9 | B23: Wrap-Up & Next QBR Date | C23: CSM | D23: 5 min | E23: Confirm action items, owners, next meeting booked | F23: Meeting follow-up sent within 24hrs | G23: Slide 18 | H23: No | I23: Yes | J23: Book on the spot before leaving the room | K23: ✅ | L23: 1:25–1:30
A26: SECTION 3 — JOINT SUCCESS PLAN · Mutual Commitments & 90-Day Roadmap
A27: Account | B27: Commitment | C27: Owner | D27: Due Date | E27: Category | F27: Priority | G27: Blocker? | H27: % Complete | I27: Status | J27: CS Notes | K27: Exec Visible? | L27: Risk if Missed
A28: Walmart | B28: Complete API integration for automated reorder | C28: Client: IT Dir | D28: Mar 01 2025 | E28: Integration | F28: P1 | G28: No | H28: 0.75 | I28: 🔄 In Progress | J28: On track per last sync | K28: Yes | L28: Delays expansion contract
A29: Walmart | B29: Deliver custom reporting dashboard (Phase 2) | C29: CSM: Cernice | D29: Mar 15 2025 | E29: Product | F29: P1 | G29: Yes | H29: 0.4 | I29: ⚠ At Risk | J29: Waiting on product team ETA | K29: Yes | L29: Client may escalate
A30: Kroger | B30: Onboard 3 new regional buyers to platform | C30: Client: Dir Proc | D30: Feb 28 2025 | E30: Adoption | F30: P2 | G30: No | H30: 0.9 | I30: ✅ On Track | J30: 2 of 3 onboarded | K30: No | L30: Minor adoption gap
A31: Kroger | B31: Submit renewal paperwork for counter-signature | C31: AE: J. Smith | D31: Mar 05 2025 | E31: Commercial | F31: P1 | G31: No | H31: 0.6 | I31: 🔄 In Progress | J31: Legal review in progress | K31: Yes | L31: Revenue at risk
A32: Meijer | B32: Conduct executive stakeholder re-mapping session | C32: CSM: T. Williams | D32: Mar 10 2025 | E32: Relationship | F32: P1 | G32: Yes | H32: 0.1 | I32: 🔴 Not Started | J32: Champion left — no replacement | K32: Yes | L32: Account at churn risk
A33: Albertsons | B33: Achieve 80%+ feature adoption across category mgmt team | C33: CSM: J. Patel | D33: Mar 31 2025 | E33: Adoption | F33: P2 | G33: No | H33: 0.55 | I33: 🔄 In Progress | J33: Scheduled training session | K33: No | L33: Low — account healthy

Sheet 👥 Team Performance
A1: CSM TEAM PERFORMANCE SCORECARD · Q1 2025 · Director: Cernice Robinson
A2: Individual KPIs · Coaching status · Development plans · Team aggregate metrics
A4: TEAM KPI TARGETS · Q1 2025 · Set by: Cernice Robinson, Feb 2025
A5: KPI | B5: Target | C5: Weight | D5: Measurement | E5: Cadence | F5: Green (Exceeds) | G5: Yellow (Meets) | H5: Red (Below) | I5: Notes
A6: Net Revenue Retention (NRR) | B6: 105% | C6: 25% | D6: ARR end vs. start of quarter | E6: Monthly | F6: ≥ 108% | G6: 100–107% | H6: < 100% | I6: Primary retention metric
A7: Gross Revenue Retention (GRR) | B7: 95% | C7: 20% | D7: Renewals ÷ total renewal opportunities | E7: Monthly | F7: ≥ 97% | G7: 93–96% | H7: < 93% | I7: Churn signal — track weekly at-risk
A8: CSAT / Customer Satisfaction | B8: 4.5/5 | C8: 20% | D8: Post-interaction CSAT survey | E8: Real-time | F8: ≥ 4.7 | G8: 4.3–4.6 | H8: < 4.3 | I8: Min 3 responses/month to be valid
A9: QBR Completion Rate | B9: 90% | C9: 15% | D9: QBRs held ÷ QBRs scheduled | E9: Monthly | F9: ≥ 95% | G9: 85–94% | H9: < 85% | I9: Enterprise = mandatory; Growth = flexible
A10: Onboarding Time-to-Value (TTV) | B10: 45 days | C10: 10% | D10: Days from contract sign to first value | E10: Per account | F10: ≤ 40d | G10: 41–50d | H10: > 50d | I10: Measured at defined value milestone
A11: Health Score Coverage | B11: 90% | C11: 10% | D11: Accounts with current health score | E11: Weekly | F11: ≥ 95% | G11: 88–94% | H11: < 88% | I11: Score must be < 30 days old
A14: INDIVIDUAL CSM PERFORMANCE · Q1 2025 YTD · Actuals vs. Targets
A15: CSM Name | B15: Seniority | C15: Accounts | D15: ARR ($K) | E15: NRR | F15: GRR | G15: CSAT | H15: QBR Rate | I15: TTV (days) | J15: Health Cov. | K15: Composite Score | L15: Rating | M15: Trend | N15: Coaching Focus | O15: Next 1:1
A16: Cernice Robinson | B16: Director | C16: 10 | D16: 8030 | E16: 1.09 | F16: 0.98 | G16: 4.8 | H16: 1 | I16: 38 | J16: 0.97 | K16: =(E16/1.05)*0.25 + (F16/0.95)*0.2 + (G16/4.5)*0.2 + H16*0.15 + ((45/MAX(I16,1))*0.1) + J16*0.1 -> 1.044594 | L16: =IF(K16>=1.05,"⭐ Exceeds",IF(K16>=0.95,"✅ Meets",IF(K16>=0.85,"⚠ Below","🔴 PIP"))) -> ✅ Meets | M16: ↑ | N16: Player-coach / Strategic accounts | O16: N/A - Director
A17: T. Williams | B17: Senior CSM | C17: 8 | D17: 3400 | E17: 1.03 | F17: 0.94 | G17: 4.4 | H17: 0.88 | I17: 44 | J17: 0.91 | K17: =(E17/1.05)*0.25 + (F17/0.95)*0.2 + (G17/4.5)*0.2 + H17*0.15 + ((45/MAX(I17,1))*0.1) + J17*0.1 -> 0.96396111 | L17: =IF(K17>=1.05,"⭐ Exceeds",IF(K17>=0.95,"✅ Meets",IF(K17>=0.85,"⚠ Below","🔴 PIP"))) -> ✅ Meets | M17: → | N17: QBR quality & exec relationships | O17: Feb 18 2025
A18: J. Patel | B18: CSM II | C18: 7 | D18: 1015 | E18: 1.06 | F18: 0.96 | G18: 4.7 | H18: 0.95 | I18: 42 | J18: 0.93 | K18: =(E18/1.05)*0.25 + (F18/0.95)*0.2 + (G18/4.5)*0.2 + H18*0.15 + ((45/MAX(I18,1))*0.1) + J18*0.1 -> 1.006018 | L18: =IF(K18>=1.05,"⭐ Exceeds",IF(K18>=0.95,"✅ Meets",IF(K18>=0.85,"⚠ Below","🔴 PIP"))) -> ✅ Meets | M18: ↑ | N18: Expansion identification | O18: Feb 20 2025
A19: M. Chen | B19: CSM I | C19: 5 | D19: 260 | E19: 0.98 | F19: 0.91 | G19: 4.2 | H19: 0.8 | I19: 52 | J19: 0.85 | K19: =(E19/1.05)*0.25 + (F19/0.95)*0.2 + (G19/4.5)*0.2 + H19*0.15 + ((45/MAX(I19,1))*0.1) + J19*0.1 -> 0.90311741 | L19: =IF(K19>=1.05,"⭐ Exceeds",IF(K19>=0.95,"✅ Meets",IF(K19>=0.85,"⚠ Below","🔴 PIP"))) -> ⚠ Below | M19: ↓ | N19: TTV reduction & health coverage | O19: Feb 19 2025
A20: A. Rodriguez | B20: Associate CSM | C20: 4 | D20: 130 | E20: 0.95 | F20: 0.89 | G20: 4 | H20: 0.75 | I20: 58 | J20: 0.82 | K20: =(E20/1.05)*0.25 + (F20/0.95)*0.2 + (G20/4.5)*0.2 + H20*0.15 + ((45/MAX(I20,1))*0.1) + J20*0.1 -> 0.86342288 | L20: =IF(K20>=1.05,"⭐ Exceeds",IF(K20>=0.95,"✅ Meets",IF(K20>=0.85,"⚠ Below","🔴 PIP"))) -> ⚠ Below | M20: ↓ | N20: Core CSM skills — PIP candidate | O20: Feb 17 2025 ⚠
A21: TEAM TOTAL / AVG | D21: =SUM(D16:D20) -> 12835 | E21: =AVERAGE(E16:E20) -> 1.022 | F21: =AVERAGE(F16:F20) -> 0.936 | G21: =AVERAGE(G16:G20) -> 4.42 | H21: =AVERAGE(H16:H20) -> 0.876 | I21: =AVERAGE(I16:I20) -> 46.8 | J21: =AVERAGE(J16:J20) -> 0.896 | K21: =AVERAGE(K16:K20) -> 0.95622267
A24: COACHING & DEVELOPMENT LOG · Director: Cernice Robinson
A25: CSM | B25: Date | C25: Type | D25: Topic | E25: Key Observations | F25: Action Items | G25: Owner | H25: Due Date | I25: Follow-Up Date | J25: Outcome | K25: Growth Area | L25: Priority
A26: T. Williams | B26: Feb 12 2025 | C26: 1:1 | D26: Exec Relationship — Meijer | E26: Executive champion left, no successor mapped | F26: 1) Map org chart 2) Request intro from AE 3) Draft re-engagement email | G26: T. Williams | H26: Feb 19 2025 | I26: Feb 26 2025 | J26: Pending | K26: Executive relationships | L26: P1
A27: M. Chen | B27: Feb 10 2025 | C27: Skills Dev | D27: Time-to-Value process | E27: 3 accounts past 50-day TTV — process unclear | F27: Shadow J. Patel's onboarding call; update TTV tracker daily | G27: M. Chen | H27: Feb 17 2025 | I27: Mar 03 2025 | J27: In Progress | K27: Onboarding execution | L27: P1
A28: A. Rodriguez | B28: Feb 08 2025 | C28: PIP Check-in | D28: Core CSM fundamentals | E28: Low QBR rate, health scores outdated, CSAT below target | F28: Weekly check-in; 3 QBRs booked by Feb 28; all scores updated | G28: A. Rodriguez | H28: Feb 28 2025 | I28: Mar 07 2025 | J28: Active | K28: Full performance improvement | L28: P1
A29: J. Patel | B29: Feb 14 2025 | C29: Growth Dev | D29: Expansion identification | E29: Strong health scores but 0 expansion convos in Q4 2024 | F29: Add expansion play to every QBR; find 1 upsell signal per account | G29: J. Patel | H29: Mar 01 2025 | I29: Mar 15 2025 | J29: In Progress | K29: Commercial acumen | L29: P2

Sheet ⚠ Churn Risk & EWS
A1: CHURN RISK & EARLY WARNING SYSTEM · Dual-Lane Detection Model · Cernice Robinson
A2: Vocal detractors: 24–48hr rapid response · Silent disengagement: behavioral composite detection · 60-day advance warning target
A4: DUAL-LANE RISK DETECTION FRAMEWORK · Signal Weights & Response Protocols
A5: LANE 1 — VOCAL DISSATISFACTION SIGNALS · Triggered: Within 24–48 hours
A6: Signal | B6: Source | C6: Weight | D6: Threshold (Trigger) | E6: Detection Method | F6: Response Owner | G6: Response SLA
A7: NPS Detractor Score (0–6) | B7: NPS Survey | C7: 35% | D7: Any score ≤ 6 | E7: Auto-alert via Gainsight | F7: CSM + Director | G7: 24 hours
A8: Negative CSAT Survey Response | B8: Support/CS Tool | C8: 25% | D8: Score < 3.5 / 5 | E8: Real-time webhook → Slack alert | F8: CSM | G8: 4 hours
A9: Escalation Submitted | B9: Support Tickets | C9: 20% | D9: Priority = P1 or P2 | E9: Ticket tag triggers CS workflow | F9: CSM + Director | G9: 2 hours
A10: Executive Complaint (email/call) | B10: CRM / Direct | C10: 15% | D10: Any executive complaint | E10: CSM manual flag in CRM | F10: Director | G10: Same day
A11: Cancellation Signal / Intent | B11: CRM / Contract | C11: 5% | D11: Renewal = 'At Risk' | E11: Opp stage change → alert | F11: Director + AE | G11: Same day
A14: LANE 2 — SILENT DISENGAGEMENT SIGNALS · Triggered: Composite ≥ 2 signals
A15: Behavioral Signal | B15: Data Source | C15: Weight | D15: Threshold (Trigger) | E15: Lookback Window | F15: Detection Method | G15: Response SLA
A16: Product Usage Decline | B16: Product Analytics | C16: 30% | D16: ≥ 20% drop week-over-week | E16: 30 days | F16: Automated weekly report | G16: 72 hours
A17: Reduced Stakeholder Touchpoints | B17: CRM / Calendar | C17: 25% | D17: < 50% of normal contact freq | E17: 60 days | F17: CRM engagement score calc | G17: 5 business days
A18: Slower Email Response Time | B18: Email / CRM | C18: 20% | D18: Response time > 2x baseline | E18: 30 days | F18: CRM tracked email analytics | G18: 5 business days
A19: Feature Adoption Plateau | B19: Product Analytics | C19: 15% | D19: 0% new feature adoption | E19: 45 days | F19: Adoption score stagnation alert | G19: 1 week
A20: Reduced Champion Access | B20: CSM Notes / CRM | C20: 10% | D20: Escalation to mgmt blocked | E20: 30 days | F20: Manual CSM flag | G20: 1 week
A23: ACTIVE CHURN RISK REGISTER · Updated Weekly · All at-risk accounts require Director review
A24: Account | B24: ARR ($K) | C24: Renewal Date | D24: Risk Lane | E24: Risk Score | F24: Vocal Signals | G24: Silent Signals | H24: Days to Renewal | I24: Intervention Owner | J24: Intervention Plan | K24: Executive Engaged? | L24: Est. Save Prob. | M24: ARR at Risk ($K) | N24: Status
A25: Safeway | B25: 880 | C25: Sep 30 2025 | D25: Lane 1 — Vocal | E25: 0.78 | F25: NPS=4, Escalation open | G25: Usage -31%, reduced touchpoints | H25: 237 | I25: Cernice Robinson | J25: Executive re-engagement + dedicated success plan | K25: Pending | L25: 60% | M25: =C25*(1-L25) -> 18372 | N25: 🔴 Critical — Active
A26: Meijer | B26: 1200 | C26: Jun 15 2025 | D26: Lane 1 + 2 — Both | E26: 0.65 | F26: Exec complaint filed | G26: Champion departed, access reduced | H26: 132 | I26: Cernice Robinson | J26: Org re-mapping + exec intro via AE sponsor | K26: Scheduled | L26: 45% | M26: =C26*(1-L26) -> 25202.65 | N26: 🔴 Critical — Escalated
A27: Trader Joes | B27: 120 | C27: Apr 01 2025 | D27: Lane 2 — Silent | E27: 0.42 | F27: None | G27: Usage -45%, 0 response to emails | H27: 57 | I27: M. Chen | J27: Win-back call + value re-demonstration | K27: No | L27: 30% | M27: =C27*(1-L27) -> 32023.6 | N27: 🔴 Critical — 57 days
A28: Sprouts | B28: 285 | C28: Aug 20 2025 | D28: Lane 2 — Silent | E28: 0.58 | F28: Low CSAT (3.2) | G28: Feature plateau, slow responses | H28: 202 | I28: J. Patel | J28: Adoption recovery plan + exec QBR schedule | K28: No | L28: 55% | M28: =C28*(1-L28) -> 20650.05 | N28: 🟠 At Risk — Monitoring
A29: Meijer Reg. | B29: 180 | C29: Jul 30 2025 | D29: Lane 2 — Silent | E29: 0.61 | F29: None | G29: Usage -22%, touchpoints -40% | H29: 181 | I29: T. Williams | J29: Proactive value review + champion mapping | K29: No | L29: 65% | M29: =C29*(1-L29) -> 16053.8 | N29: 🟠 At Risk — Monitoring
A30: TOTAL ARR AT RISK | B30: =SUM(B25:B29) -> 2665 | M30: =SUM(M25:M29) -> 112302.1 | N30: ← Projected ARR loss if no intervention
A32: INTERVENTION PLAYBOOKS · Director-Level Protocols by Risk Severity
A33: Risk Level | B33: Trigger | C33: Day 1 Action | D33: Day 3 Action | E33: Day 7 Action | F33: Day 14 Action | G33: Day 30 Action | H33: Executive Loop? | I33: Escalation Path | J33: Success Metric
A34: 🔴 Critical (< 50) | B34: Any P1 signal OR composite < 50 | C34: CSM calls within 2 hrs; Director notified | D34: Director joins CSM on account call | E34: Internal war room: CSM + Director + AE + PM | F34: Executive sponsor engaged; recovery plan delivered | G34: 30-day health check; renewal risk assessed | H34: Yes — mandatory | I34: Director → VP CS → CRO if unresolved | J34: Health score ≥ 60 within 60 days
A35: 🟠 At Risk (50–69) | B35: Composite signal ≥ 2 OR score 50–69 | C35: CSM proactive value call scheduled | D35: Personalized success plan delivered | E35: QBR accelerated; adoption review completed | F35: Director reviews progress; CSM coached | G35: Health check; expansion signal scan | H35: If score declining | I35: CSM → Director if no improvement | J35: Score ≥ 70 within 45 days
A36: 🟡 Monitor (70–84) | B36: Downward trend ≥ 2 consecutive months | C36: CSM check-in: usage & open items | D36: CSAT pulse sent; feature tips shared | E36: QBR prep accelerated if renewal < 90 days | F36: Review expansion pipeline | G36: Standard QBR cycle | H36: No unless exec asks | I36: CSM → Director if 2+ months declining | J36: Score ≥ 85 within 60 days

Sheet 🚀 Onboarding Tracker
A1: ONBOARDING MILESTONE TRACKER · 30-60-90 Day Framework · Director: Cernice Robinson
A2: Target TTV: 45 days · Milestone-based checkpoints · Auto-alerts at 110% of target days · All new accounts enter this tracker at contract signature
A4: STANDARD MILESTONE FRAMEWORK · Applies to all tiers — Enterprise has additional milestones
A5: Phase | B5: Day Target | C5: Milestone | D5: Owner | E5: Deliverable | F5: Success Criteria | G5: Tools / Systems | H5: Enterprise Add-On? | I5: Notes
A6: Day 1 | B6: 1 | C6: Contract signed — onboarding triggered | D6: AE → CSM | E6: Handoff brief + account summary | F6: CSM contacted within 4 hrs of signature | G6: Gainsight / CRM | H6: No | I6: AE provides deal notes + stakeholder map
A7: Day 3 | B7: 3 | C7: Kickoff call completed | D7: CSM | E7: Kickoff deck + success plan draft | F7: All stakeholders confirmed; goals documented | G7: Zoom / Slides | H7: No | I7: Send agenda 48hrs in advance
A8: Day 7 | B8: 7 | C8: Technical setup & access provisioned | D8: CSM + IT | E8: Setup checklist completed | F8: 100% of users have working access | G8: IT / Admin portal | H8: Yes | I8: Enterprise: SSO + API integration
A9: Day 10 | B9: 10 | C9: Training session 1 (core users) completed | D9: CSM | E9: Training recording + resource guide | F9: ≥ 80% of core users trained | G9: LMS / Zoom | H9: No | I9: Track attendance; send recording same day
A10: Day 14 | B10: 14 | C10: First value milestone achieved | D10: CSM | E10: Value milestone confirmation note | F10: Client confirms 1 defined value outcome | G10: CS Platform / Email | H10: No | I10: Agree on value def. at kickoff
A11: Day 21 | B11: 21 | C11: Admin & power user training complete | D11: CSM | E11: Certification summary | F11: All admins certified; power users active | G11: LMS / Admin portal | H11: Yes | I11: Enterprise: custom admin training
A12: Day 30 | B12: 30 | C12: 30-day health check & success plan review | D12: CSM + Dir | E12: 30-day report card | F12: Health score ≥ 70; goals on track | G12: Gainsight / Slides | H12: Yes | I12: Director joins enterprise 30-day reviews
A13: Day 45 | B13: 45 | C13: Time-to-Value (TTV) milestone achieved | D13: CSM | E13: TTV confirmation + ROI summary | F13: Client confirms value; CSAT ≥ 4.2 | G13: CS Platform / Survey | H13: No | I13: Document for case study if ≥ 4.5 CSAT
A14: Day 60 | B14: 60 | C14: Integration & advanced feature adoption | D14: CSM | E14: Feature adoption report | F14: ≥ 60% feature utilization | G14: Product Analytics | H14: Yes | I14: Enterprise: integration health verified
A15: Day 90 | B15: 90 | C15: First QBR completed | D15: CSM + Dir | E15: QBR deck + joint success plan (next 90 days) | F15: All success plan items have owners + dates | G15: QBR Tab ↗ | H15: Yes | I15: Director attends all enterprise 90-day QBRs
A18: ACTIVE ONBOARDING ACCOUNTS · Q1 2025 · New accounts in current onboarding cycle
A19: Account | B19: Tier | C19: CSM | D19: Contract Date | E19: Day # | F19: TTV Target | G19: Current Phase | H19: % Milestones Done | I19: Kickoff | J19: Setup | K19: Training | L19: First Value | M19: 30-Day Check | N19: TTV Achieved? | O19: CSAT | P19: Status / Alert
A20: Sprouts Expansion | B20: Mid-Market | C20: J. Patel | D20: Jan 06 2025 | E20: 39 | F20: 45 | G20: Day 30–45 Phase | H20: =COUNTIF(I20:M20,"✅")/5 -> 1 | I20: ✅ | J20: ✅ | K20: ✅ | L20: ✅ | M20: ✅ | N20: 🔄 Pending | O20: 4.4 | P20: 🟢 On Track
A21: Fresh Market | B21: Mid-Market | C21: J. Patel | D21: Jan 20 2025 | E21: 25 | F21: 45 | G21: Day 21–30 Phase | H21: =COUNTIF(I21:M21,"✅")/5 -> 0.6 | I21: ✅ | J21: ✅ | K21: ✅ | L21: 🔄 | M21: ⏳ | N21: ⏳ | O21: 4.6 | P21: 🟢 On Track
A22: Aldi Expansion | B22: Growth | C22: M. Chen | D22: Feb 01 2025 | E22: 13 | F22: 45 | G22: Day 10–14 Phase | H22: =COUNTIF(I22:M22,"✅")/5 -> 0.4 | I22: ✅ | J22: ✅ | K22: 🔄 | L22: ⏳ | M22: ⏳ | N22: ⏳ | O22: — | P22: 🟢 On Track
A23: New Client A | B23: Enterprise | C23: T. Williams | D23: Jan 10 2025 | E23: 35 | F23: 45 | G23: Day 30 Check | H23: =COUNTIF(I23:M23,"✅")/5 -> 0.8 | I23: ✅ | J23: ✅ | K23: ✅ | L23: ✅ | M23: 🔄 | N23: ⏳ | O23: 4.1 | P23: 🟡 Watch — Day 30 due
A24: New Client B | B24: Growth | C24: M. Chen | D24: Dec 15 2024 | E24: 61 | F24: 45 | G24: TTV Overdue | H24: =COUNTIF(I24:M24,"✅")/5 -> 1 | I24: ✅ | J24: ✅ | K24: ✅ | L24: ✅ | M24: ✅ | N24: ❌ Overdue | O24: 3.8 | P24: 🔴 TTV Exceeded — Action Required
A27: ONBOARDING PERFORMANCE KPIs · Q1 2025 YTD
A28: KPI | B28: Target | C28: Actual | D28: vs. Target | E28: Trend | F28: Notes
A29: Average Time-to-Value | B29: 45 days | C29: 43 days | D29: =C29 -> 43 days | E29: ↓ Improving | F29: 3-day improvement vs. Q4 2024 (46 days avg)
A30: Kickoff-to-First-Value Rate | B30: 90% | C30: 94% | D30: =C30 -> 94% | E30: ↑ Improving | F30: 4 of 4 completed accounts hit first value on time
A31: 30-Day Health Score ≥ 70 | B31: 85% | C31: 80% | D31: =C31 -> 80% | E31: → Stable | F31: 1 account below threshold — coaching in progress
A32: Onboarding CSAT | B32: 4.3 | C32: 4.4 | D32: =C32 -> 4.4 | E32: ↑ Improving | F32: Above target — new agenda template driving improvement
A33: Day-1 Contact Rate | B33: 100% | C33: 100% | D33: =C33 -> 100% | E33: → Stable | F33: All new accounts contacted within 4 hrs of signature
A34: Milestone Completion Rate | B34: 90% | C34: 87% | D34: =C34 -> 87% | E34: → Stable | F34: 3% below target — 1 enterprise account delayed by client IT
